setup.py
secure_file_transfer/__init__.py
secure_file_transfer/client.py
secure_file_transfer/server.py
secure_file_transfer.egg-info/PKG-INFO
secure_file_transfer.egg-info/SOURCES.txt
secure_file_transfer.egg-info/dependency_links.txt
secure_file_transfer.egg-info/top_level.txt