Metadata-Version: 2.1
Name: secure-file-transfer
Version: 1.0.0
Summary: A secure file transfer protocol with compression and resumption support.
Home-page: https://github.com/sanskary2303/secure_file_transfer
Author: Sanskar Yaduka
Author-email: sanskary22@iitk.ac.in
